annotation_tool/__init__.py
annotation_tool/asgi.py
annotation_tool/settings.py
annotation_tool/urls.py
annotation_tool/wsgi.py
annotator/__init__.py
annotator/admin.py
annotator/apps.py
annotator/models.py
annotator/tests.py
annotator/urls.py
annotator/views.py
deeplabelnet_launcher/__init__.py
deeplabelnet_launcher/__main__.py
deeplabelnet-0.1.16.dist-info/METADATA
deeplabelnet-0.1.16.dist-info/WHEEL
deeplabelnet-0.1.16.dist-info/entry_points.txt
deeplabelnet-0.1.16.dist-info/top_level.txt
deeplabelnet-0.1.16.dist-info/RECORD
